{
    "data": {
        "workbooks": [
            {
                "id": "735489fe-40e8-2c65-6fdc-c4d867c5cfdf",
                "luid": "f495db95-3e95-4462-a116-f692e796781d",
                "name": "Compensation Dashboard",
                "description": "",
                "createdAt": "2024-04-18T16:47:13Z",
                "site": {
                    "luid": "959ed77c-9270-4d54-9505-2a21e9c5a5b1"
                },
                "projectName": "Human Resources",
                "projectVizportalUrlId": "593730",
                "owner": {
                    "id": "bfea471b-f964-fa51-c919-03df6d6d0876"
                },
                "uri": "sites/3469/workbooks/4635686",
                "upstreamDatasources": []
            },
            {
                "id": "8820af0c-5eeb-ce4d-fb51-f1337f7cf165",
                "luid": "eb33160b-5c29-49ab-9ec3-fb04c571fa1c",
                "name": "Admin Insights Starter",
                "description": "",
                "createdAt": "2024-04-17T16:06:03Z",
                "site": {
                    "luid": "959ed77c-9270-4d54-9505-2a21e9c5a5b1"
                },
                "projectName": "Admin Insights",
                "projectVizportalUrlId": "591368",
                "owner": {
                    "id": "ea79e50a-aba0-4acf-f51f-2a7fc001920c"
                },
                "uri": "sites/3469/workbooks/4633563",
                "upstreamDatasources": [
                    {
                        "id": "58369c00-736e-70f8-408d-f34af0610a55",
                        "luid": "7754aefa-9f74-4b89-b7ae-af6cf42adbdc",
                        "name": "TS Users"
                    },
                    {
                        "id": "953e9c41-669f-b13a-8668-95e6e9b4cf39",
                        "luid": "1915d105-272b-4ea7-b9ef-f6bca531c074",
                        "name": "Groups"
                    },
                    {
                        "id": "be5ef4e3-a8c7-ec1e-4a2b-0cfddfc6bc85",
                        "luid": "53ee3dfa-3674-4d94-baee-be915c870e66",
                        "name": "Site Content"
                    },
                    {
                        "id": "fbd6551c-4418-73ba-674b-9574a50f95e9",
                        "luid": "398435b7-87f9-4ee6-8252-14f5b031e534",
                        "name": "TS Events"
                    }
                ]
            },
            {
                "id": "96366e93-f040-6a9b-c857-2a5076a12957",
                "luid": "a443c990-469e-42e3-803d-34bf767f711e",
                "name": "Diversity and Equity Payroll Report",
                "description": "",
                "createdAt": "2024-04-18T17:05:39Z",
                "site": {
                    "luid": "959ed77c-9270-4d54-9505-2a21e9c5a5b1"
                },
                "projectName": "Human Resources",
                "projectVizportalUrlId": "593730",
                "owner": {
                    "id": "bfea471b-f964-fa51-c919-03df6d6d0876"
                },
                "uri": "sites/3469/workbooks/4635719",
                "upstreamDatasources": []
            },
            {
                "id": "9bec027c-049c-cb71-a378-4c4ba28bb232",
                "luid": "4cb14ccd-2b62-466c-9c14-b31ea46b32fc",
                "name": "Superstore",
                "description": "",
                "createdAt": "2024-04-16T23:58:10Z",
                "site": {
                    "luid": "959ed77c-9270-4d54-9505-2a21e9c5a5b1"
                },
                "projectName": "Samples",
                "projectVizportalUrlId": "590933",
                "owner": {
                    "id": "bfea471b-f964-fa51-c919-03df6d6d0876"
                },
                "uri": "sites/3469/workbooks/4632269",
                "upstreamDatasources": []
            },
            {
                "id": "baa64586-2ce8-58a5-11a2-21b4aa0cd82f",
                "luid": "ffdd85eb-c9e1-4956-b05f-620bd7917fcd",
                "name": "World Indicators",
                "description": "",
                "createdAt": "2024-04-16T23:58:13Z",
                "site": {
                    "luid": "959ed77c-9270-4d54-9505-2a21e9c5a5b1"
                },
                "projectName": "Samples",
                "projectVizportalUrlId": "590933",
                "owner": {
                    "id": "bfea471b-f964-fa51-c919-03df6d6d0876"
                },
                "uri": "sites/3469/workbooks/4632270",
                "upstreamDatasources": []
            },
            {
                "id": "e0631136-8314-5fd2-9aea-041c4a0f2dfe",
                "luid": "e1264abc-1ee7-4ac7-aec0-cbb56be6137d",
                "name": "superstore",
                "description": "An intricate view of sales activities and customer engagements. Within this dataset lies a plethora of products, spanning office supplies, furniture, and cutting-edge technology, all meticulously tracked across various regions and customer demographics. Every entry in this dataset reflects a tangible transaction, detailing vital information such as product categories, quantities sold, revenue generated, shipping logistics, and customer profiles. Leveraging the inherent capabilities of the dataset, analysts can seamlessly delve into this wealth of information to uncover actionable insights, ranging from sales patterns to profitability metrics and customer purchasing behaviors. This authentic portrayal of a company's day-to-day operations serves as an invaluable resource for professionals seeking to refine their analytical prowess and harness the power of data-driven decision-making in a real-world business context.",
                "createdAt": "2024-04-17T01:57:44Z",
                "site": {
                    "luid": "959ed77c-9270-4d54-9505-2a21e9c5a5b1"
                },
                "projectName": "superstore",
                "projectVizportalUrlId": "590934",
                "owner": {
                    "id": "bfea471b-f964-fa51-c919-03df6d6d0876"
                },
                "uri": "sites/3469/workbooks/4632436",
                "upstreamDatasources": []
            }
        ]
    }
}
